xpuding_mcp_demo/__init__.py
xpuding_mcp_demo-0.1.0.dist-info/METADATA
xpuding_mcp_demo-0.1.0.dist-info/WHEEL
xpuding_mcp_demo-0.1.0.dist-info/entry_points.txt
xpuding_mcp_demo-0.1.0.dist-info/RECORD
