Metadata-Version: 2.4
Name: xpuding-mcp-demo
Version: 0.1.0
Summary: Add your description here
Author-email: Xpud1n9 <code14pudding@163.com>
Requires-Python: >=3.11
Requires-Dist: mcp[cli]>=1.14.0
